sqlamock/__init__.py
sqlamock/async_connection_provider.py
sqlamock/async_db_mock.py
sqlamock/async_fixtures.py
sqlamock/async_snapshot.py
sqlamock/connection_provider.py
sqlamock/data_interface.py
sqlamock/db_mock.py
sqlamock/fixtures.py
sqlamock/patches.py
sqlamock/snapshot.py
sqlamock/types.py
sqlamock-0.3.0.dist-info/METADATA
sqlamock-0.3.0.dist-info/WHEEL
sqlamock-0.3.0.dist-info/entry_points.txt
sqlamock-0.3.0.dist-info/RECORD
