Metadata-Version: 2.4
Name: sqlamock
Version: 0.3.0
Summary: Provides mocks for SQLAlchemy using in-memory / on-file sqlite databases with growing support for PostgreSQL
Author: Chris Lee
Author-email: chris@cosmosnexus.co
Requires-Python: >=3.10,<4
Classifier: Programming Language :: Python :: 3
Classifier: Programming Language :: Python :: 3.10
Classifier: Programming Language :: Python :: 3.11
Classifier: Programming Language :: Python :: 3.12
Classifier: Programming Language :: Python :: 3.13
Classifier: Programming Language :: Python :: 3.14
Provides-Extra: async
Requires-Dist: aiosqlite (>=0.20.0,<0.21.0) ; extra == "async"
Requires-Dist: sqlalchemy (>=2.0.36,<3.0.0)
